ArbolBinarioBusqueda/__init__.py
ArbolBinarioBusqueda-0.2.6.dist-info/LICENSE
ArbolBinarioBusqueda-0.2.6.dist-info/METADATA
ArbolBinarioBusqueda-0.2.6.dist-info/WHEEL
ArbolBinarioBusqueda-0.2.6.dist-info/top_level.txt
ArbolBinarioBusqueda-0.2.6.dist-info/RECORD
